mcp_pinot/__init__.py
mcp_pinot/prompts.py
mcp_pinot/server.py
mcp_pinot/utils/__init__.py
mcp_pinot/utils/pinot_client.py
mcp_pinot_server-0.1.0.dist-info/licenses/LICENSE
mcp_pinot_server-0.1.0.dist-info/METADATA
mcp_pinot_server-0.1.0.dist-info/WHEEL
mcp_pinot_server-0.1.0.dist-info/entry_points.txt
mcp_pinot_server-0.1.0.dist-info/top_level.txt
mcp_pinot_server-0.1.0.dist-info/RECORD
