Metadata-Version: 2.4
Name: mcp-pinot-server
Version: 0.1.0
Summary: A production-grade MCP server for Apache Pinot
License-Expression: Apache-2.0
Project-URL: Home, http://github.com/startreedata/mcp-pinot
Requires-Python: >=3.10
License-File: LICENSE
Requires-Dist: mcp[cli]>=1.6.0
Requires-Dist: pinotdb>=5.6.0
Requires-Dist: uvicorn>=0.34.0
Requires-Dist: python-dotenv>=1.0.1
Requires-Dist: httpx>=0.27.2
Requires-Dist: pandas>=2.2.3
Requires-Dist: requests>=2.32.3
Provides-Extra: dev
Requires-Dist: pytest; extra == "dev"
Requires-Dist: pytest-asyncio; extra == "dev"
Requires-Dist: pytest-mock; extra == "dev"
Requires-Dist: pytest-cov; extra == "dev"
Dynamic: license-file
